MANIFEST.in
setup.py
bcrypt/__init__.py
bcrypt/bcrypt.c
bcrypt/bcrypt_python.c
bcrypt/blowfish.c
bcrypt/pybc_blf.h
python_bcrypt.egg-info/PKG-INFO
python_bcrypt.egg-info/SOURCES.txt
python_bcrypt.egg-info/dependency_links.txt
python_bcrypt.egg-info/top_level.txt
test/test.py