Metadata-Version: 1.0
Name: python-bcrypt
Version: 0.3.1
Summary: Blowfish password hashing
Home-page: https://github.com/DisruptiveLabs/python-bcrypt
Author: Damien Miller, maintained by @kageurufu
Author-email: kage.urufu@gmail.com
License: BSD
Platform: UNKNOWN
